torf/__init__.py
torf/__init__.pyi
torf/_errors.py
torf/_errors.pyi
torf/_flatbencode.py
torf/_generate.py
torf/_magnet.py
torf/_magnet.pyi
torf/_reuse.py
torf/_stream.py
torf/_stream.pyi
torf/_torrent.py
torf/_torrent.pyi
torf/_utils.py
torf/_utils.pyi
torf/py.typed
torf-4.3.1.dist-info/licenses/LICENSE
torf-4.3.1.dist-info/METADATA
torf-4.3.1.dist-info/WHEEL
torf-4.3.1.dist-info/top_level.txt
torf-4.3.1.dist-info/RECORD
