Metadata-Version: 2.4
Name: torf
Version: 4.3.1
Summary: Python 3 module for creating and parsing torrent files and magnet URIs
Author-email: Random User <rndusr@posteo.de>
License: GPL-3.0-or-later
Project-URL: Repository, https://github.com/rndusr/torf
Project-URL: Documentation, https://torf.readthedocs.io/
Project-URL: Bug Tracker, https://github.com/rndusr/torf/issues
Project-URL: Changelog, https://raw.githubusercontent.com/rndusr/torf/master/CHANGELOG
Keywords: bittorrent,torrent,magnet
Classifier: Development Status :: 5 - Production/Stable
Classifier: Intended Audience :: Developers
Classifier: License :: OSI Approved :: GNU General Public License v3 or later (GPLv3+)
Classifier: Operating System :: OS Independent
Classifier: Programming Language :: Python :: 3.8
Classifier: Programming Language :: Python :: 3.9
Classifier: Programming Language :: Python :: 3.10
Classifier: Programming Language :: Python :: 3.11
Classifier: Programming Language :: Python :: 3.12
Classifier: Programming Language :: Python :: 3.13
Classifier: Programming Language :: Python :: 3.14
Classifier: Topic :: Software Development :: Libraries
Requires-Python: >=3.8
License-File: LICENSE
Provides-Extra: dev
Requires-Dist: pytest; extra == "dev"
Requires-Dist: pytest-xdist; extra == "dev"
Requires-Dist: pytest-httpserver; extra == "dev"
Requires-Dist: pytest-mock; extra == "dev"
Requires-Dist: tox; extra == "dev"
Requires-Dist: coverage; extra == "dev"
Requires-Dist: pytest-cov; extra == "dev"
Requires-Dist: ruff; extra == "dev"
Requires-Dist: flake8; extra == "dev"
Requires-Dist: isort; extra == "dev"
Requires-Dist: mypy; extra == "dev"
Dynamic: license-file
